autogptq_cuda_256.cpython-311-x86_64-linux-gnu.so
exllamav2_kernels.cpython-311-x86_64-linux-gnu.so
exllama_kernels.cpython-311-x86_64-linux-gnu.so
autogptq_cuda_64.cpython-311-x86_64-linux-gnu.so
autogptq_marlin_cuda.cpython-311-x86_64-linux-gnu.so
auto_gptq/__init__.py
auto_gptq/quantization/__init__.py
auto_gptq/quantization/quantizer.py
auto_gptq/quantization/gptq.py
auto_gptq/nn_modules/fused_llama_mlp.py
auto_gptq/nn_modules/__init__.py
auto_gptq/nn_modules/fused_llama_attn.py
auto_gptq/nn_modules/_fused_base.py
auto_gptq/nn_modules/fused_gptj_attn.py
auto_gptq/nn_modules/qlinear/qlinear_cuda_old.py
auto_gptq/nn_modules/qlinear/__init__.py
auto_gptq/nn_modules/qlinear/qlinear_exllama.py
auto_gptq/nn_modules/qlinear/qlinear_exllamav2.py
auto_gptq/nn_modules/qlinear/qlinear_qigen.py
auto_gptq/nn_modules/qlinear/qlinear_cuda.py
auto_gptq/nn_modules/qlinear/qlinear_triton.py
auto_gptq/nn_modules/qlinear/qlinear_marlin.py
auto_gptq/nn_modules/triton_utils/kernels.py
auto_gptq/nn_modules/triton_utils/__init__.py
auto_gptq/nn_modules/triton_utils/custom_autotune.py
auto_gptq/nn_modules/triton_utils/mixin.py
auto_gptq/modeling/gpt2.py
auto_gptq/modeling/stablelmepoch.py
auto_gptq/modeling/_const.py
auto_gptq/modeling/baichuan.py
auto_gptq/modeling/llama.py
auto_gptq/modeling/mistral.py
auto_gptq/modeling/__init__.py
auto_gptq/modeling/gptj.py
auto_gptq/modeling/opt.py
auto_gptq/modeling/gpt_bigcode.py
auto_gptq/modeling/gpt_neox.py
auto_gptq/modeling/codegen.py
auto_gptq/modeling/yi.py
auto_gptq/modeling/moss.py
auto_gptq/modeling/mixtral.py
auto_gptq/modeling/_utils.py
auto_gptq/modeling/auto.py
auto_gptq/modeling/xverse.py
auto_gptq/modeling/decilm.py
auto_gptq/modeling/gemma.py
auto_gptq/modeling/_base.py
auto_gptq/modeling/rw.py
auto_gptq/modeling/longllama.py
auto_gptq/modeling/bloom.py
auto_gptq/modeling/qwen2.py
auto_gptq/modeling/internlm.py
auto_gptq/modeling/qwen.py
auto_gptq/eval_tasks/__init__.py
auto_gptq-0.7.1.dist-info/top_level.txt
auto_gptq-0.7.1.dist-info/WHEEL
auto_gptq-0.7.1.dist-info/LICENSE
auto_gptq-0.7.1.dist-info/METADATA
auto_gptq-0.7.1.dist-info/RECORD
