Metadata-Version: 2.1
Name: auto_gptq
Version: 0.7.1
Summary: An easy-to-use LLMs quantization package with user-friendly apis, based on GPTQ algorithm.
Home-page: https://github.com/PanQiWei/AutoGPTQ
Author: PanQiWei
Keywords: gptq,quantization,large-language-models,transformers
Platform: windows
Platform: linux
Classifier: Environment :: GPU :: NVIDIA CUDA :: 11.7
Classifier: Environment :: GPU :: NVIDIA CUDA :: 11.8
Classifier: Environment :: GPU :: NVIDIA CUDA :: 12
Classifier: License :: OSI Approved :: MIT License
Classifier: Natural Language :: Chinese (Simplified)
Classifier: Natural Language :: English
Classifier: Programming Language :: Python :: 3.8
Classifier: Programming Language :: Python :: 3.9
Classifier: Programming Language :: Python :: 3.10
Classifier: Programming Language :: Python :: 3.11
Classifier: Programming Language :: C++
Requires-Python: >=3.8.0
License-File: LICENSE
Requires-Dist: accelerate >=0.26.0
Requires-Dist: datasets
Requires-Dist: sentencepiece
Requires-Dist: numpy
Requires-Dist: rouge
Requires-Dist: gekko
Requires-Dist: torch >=1.13.0
Requires-Dist: safetensors
Requires-Dist: transformers >=4.31.0
Requires-Dist: peft >=0.5.0
Requires-Dist: tqdm
Provides-Extra: quality
Requires-Dist: ruff ==0.1.5 ; extra == 'quality'
Provides-Extra: test
Requires-Dist: pytest ; extra == 'test'
Requires-Dist: parameterized ; extra == 'test'
Provides-Extra: triton
Requires-Dist: triton ==2.0.0 ; extra == 'triton'
